gnuper/__init__.py
gnuper/attributes.py
gnuper/attributes_classes.py
gnuper/bandicoot.py
gnuper/hdfs.py
gnuper/mockup_attributes.py
gnuper/preprocessing_functions.py
gnuper/preprocessing_script.py
gnuper/queries.py
gnuper/sdf.py
gnuper/spark_data_frames.py
gnuper/queries/__init__.py
gnuper/queries/general.py
gnuper/queries/level0.py
gnuper/queries/level1.py
gnuper/queries/level2.py
gnuper/queries/level3.py
gnuper-0.0.3.dist-info/METADATA
gnuper-0.0.3.dist-info/RECORD
gnuper-0.0.3.dist-info/WHEEL
gnuper-0.0.3.dist-info/top_level.txt
