Metadata-Version: 2.1
Name: gnuper
Version: 0.0.3
Summary: Open Source Package for Mobile Phone Metadata Preprocessing
Home-page: https://gitlab.com/knuper/gnuper
Author: Fabian Bruckschen
Author-email: fabian@knuper.com
License: UNKNOWN
Platform: UNKNOWN
Classifier: Programming Language :: Python :: 3
Classifier: License :: OSI Approved :: MIT License
Classifier: Operating System :: OS Independent
Requires-Dist: bandicoot (==0.5.3)
Requires-Dist: glob2 (==0.5)
Requires-Dist: numpy
Requires-Dist: numpydoc
Requires-Dist: pandas (==0.23.3)
Requires-Dist: py4j (==0.10.7)
Requires-Dist: pyarrow
Requires-Dist: pyspark (==2.3.1)
Requires-Dist: tqdm
